renogy_lib_python/__init__.py
renogy_lib_python/battery_protocol.py
renogy_lib_python/cal_tools.py
renogy_lib_python/controller_protocol.py
renogy_lib_python/modbus_comm.py
renogy_modbus_lib_python-0.1.10.dist-info/licenses/LICENSE
renogy_modbus_lib_python-0.1.10.dist-info/METADATA
renogy_modbus_lib_python-0.1.10.dist-info/WHEEL
renogy_modbus_lib_python-0.1.10.dist-info/top_level.txt
renogy_modbus_lib_python-0.1.10.dist-info/RECORD
