Metadata-Version: 2.4
Name: renogy-modbus-lib-python
Version: 0.1.10
Summary: Renogy Bluetooth SDK for Python
Home-page: https://github.com/yourusername/RenogyBT_forPythonSDK
Author: Renogy
Author-email: your.email@example.com
License: MIT
Classifier: Programming Language :: Python :: 3
Classifier: License :: OSI Approved :: MIT License
Classifier: Operating System :: OS Independent
Requires-Python: >=3.7
License-File: LICENSE
Requires-Dist: pyserial>=3.5
Requires-Dist: bleak>=0.19.0
Dynamic: author
Dynamic: author-email
Dynamic: classifier
Dynamic: description
Dynamic: description-content-type
Dynamic: home-page
Dynamic: license
Dynamic: license-file
Dynamic: requires-dist
Dynamic: requires-python
Dynamic: summary
